{
  "locations": [
    { "id": 1, "name": "Columbia" },
    { "id": 2, "name": "Lawrenceburg" },
    { "id": 3, "name": "Lewisburg" },
    { "id": 4, "name": "Williamson" },
    { "id": 5, "name": "Off-Site" }
  ],

  "employees": [
    { "id": 1, "name": "Michelle", "is_admin": true, "is_tech": false },
    { "id": 2, "name": "Josh", "is_admin": false, "is_tech": false },
    { "id": 3, "name": "Eric", "is_admin": true, "is_tech": false },
    { "id": 4, "name": "Isaiah", "is_admin": false, "is_tech": false },
    { "id": 5, "name": "Dale", "is_admin": true, "is_tech": true },
    { "id": 6, "name": "Javon", "is_admin": true, "is_tech": true }
  ],

  "irregularities": [
    { "id": 1, "code": "IRR0001", "type": "Unauthorized Materials", "label": "IRR0001 – Unauthorized Materials" },
    { "id": 2, "code": "IRR0002", "type": "Examinee Misconduct", "label": "IRR0002 – Examinee Misconduct" },
    { "id": 3, "code": "IRR0003", "type": "Technical Failure", "label": "IRR0003 – Technical Failure" },
    { "id": 4, "code": "IRR0004", "type": "Environmental Disruption", "label": "IRR0004 – Environmental Disruption" },
    { "id": 5, "code": "IRR0005", "type": "Policy Violation", "label": "IRR0005 – Policy Violation" }
  ],

  "ticket_types": [
    { "id": 1, "label": "Faculty Request" },
    { "id": 2, "label": "Student Issue" },
    { "id": 3, "label": "Accessibility Coordination" },
    { "id": 4, "label": "Vendor Test Coordination" },
    { "id": 5, "label": "Internal Follow-Up" },
    { "id": 6, "label": "Exam Delivery / Return" },
    { "id": 7, "label": "System Error / Incident" },
    { "id": 8, "label": "Irregularity Generated" },
    { "id": 9, "label": "Exam Intake" },
    { "id": 10, "label": "Other", "has_conditional_text": true }
  ],

  "statuses": [
    { "id": 1, "label": "Open" },
    { "id": 2, "label": "Pending" },
    { "id": 3, "label": "Closed" },
    { "id": 4, "label": "On Hold" }
  ],

  "priorities": [
    { "id": 1, "label": "Low" },
    { "id": 2, "label": "Normal" },
    { "id": 3, "label": "High" },
    { "id": 4, "label": "Urgent" }
  ],

  "origin_sources": [
    { "id": 1, "label": "Submitted by form" },
    { "id": 2, "label": "Created from email" },
    { "id": 3, "label": "Created from Irregularity" },
    { "id": 4, "label": "Created from Incident" },
    { "id": 5, "label": "Created by employee" },
    { "id": 6, "label": "Imported from external system" }
  ],

  "initial_comm_types": [
    { "id": 1, "label": "Email (pasted-in or auto-captured)" },
    { "id": 2, "label": "Phone call" },
    { "id": 3, "label": "Walk-in" },
    { "id": 4, "label": "Form submission" },
    { "id": 5, "label": "Vendor portal communication" },
    { "id": 6, "label": "Other" }
  ],

  "test_types": [
    { "id": 1, "label": "Accuplacer" },
    { "id": 2, "label": "HiSET" },
    { "id": 3, "label": "Pearson" },
    { "id": 4, "label": "CLEP" },
    { "id": 5, "label": "Faculty Test" },
    { "id": 6, "label": "TN eCampus" },
    { "id": 7, "label": "Outside Institution" }
  ],

  "test_mediums": [
    { "id": 1, "label": "Paper exam" },
    { "id": 2, "label": "Online exam" }
  ],

  "email_templates": [],

  "testing_events": [
    { "id": 1, "label": "Spring 2026 – Accuplacer Session 1" },
    { "id": 2, "label": "Spring 2026 – HiSET Cohort A" },
    { "id": 3, "label": "Spring 2026 – CLEP Exam Block" },
    { "id": 4, "label": "Spring 2026 – Pearson Testing Window" }
  ],

  "tickets": [
    {
      "id": 1,
      "created_at": "2026-04-18T09:15:00",
      "updated_at": "2026-04-18T09:15:00",
      "closed_at": null,
      "opened_by_staff_id": 1,
      "ticket_type": "Faculty Request",
      "status": "Open",
      "priority": "Normal",
      "origin_source": "Created from email",
      "location_id": 1,
      "brief_summary": "Faculty requesting makeup exam for student who missed scheduled BIOL 201 exam",
      "examinee_id": null,
      "irregularity_id": null,
      "testing_event_id": null,
      "faculty_name": "Dr. Sarah Nguyen",
      "faculty_email": "snguyen@columbiastate.edu",
      "external_contact_name": null,
      "external_contact_email": null,
      "initial_comm_type": "Email (pasted-in or auto-captured)",
      "original_message": "Hi Testing Services, I have a student who was sick during the scheduled exam period and unable to attend. Can you accommodate a makeup exam for BIOL 201? The student has documentation from the campus health center.",
      "exam_type": null,
      "test_medium": null,
      "accommodated_exam": false,
      "exam_returned": false,
      "exam_returned_at": null,
      "requires_email": false,
      "email_subject": null,
      "email_body": null,
      "email_recipients": null,
      "log_notes": "04/18/2026 – Received faculty email. Forwarded to scheduling staff for availability check.",
      "resolution_summary": null,
      "category_tags": "faculty, makeup, biology"
    },
    {
      "id": 2,
      "created_at": "2026-04-17T13:42:00",
      "updated_at": "2026-04-19T10:00:00",
      "closed_at": null,
      "opened_by_staff_id": 2,
      "ticket_type": "Student Issue",
      "status": "Pending",
      "priority": "High",
      "origin_source": "Created by employee",
      "location_id": 3,
      "brief_summary": "Student reports Accuplacer score not appearing on enrollment portal – ID 9827341",
      "examinee_id": "9827341",
      "irregularity_id": null,
      "testing_event_id": null,
      "faculty_name": null,
      "faculty_email": null,
      "external_contact_name": null,
      "external_contact_email": null,
      "initial_comm_type": "Walk-in",
      "original_message": "Student came in person on 04/17 to report that after completing Accuplacer last week, their score has not appeared in the enrollment system. Student is unable to complete course registration without a placement score.",
      "exam_type": "Accuplacer",
      "test_medium": null,
      "accommodated_exam": false,
      "exam_returned": false,
      "exam_returned_at": null,
      "requires_email": true,
      "email_subject": "Re: Accuplacer Score Not Posted – Student ID 9827341",
      "email_body": "Hi Registrar's Office, we have a student whose Accuplacer score from 04/11 has not posted to the enrollment system. Student ID: 9827341. Please advise on next steps.",
      "email_recipients": "registrar@columbiastate.edu",
      "log_notes": "04/17/2026 – Student walked in to report missing score.\n04/19/2026 – Emailed registrar office. Awaiting response.",
      "resolution_summary": null,
      "category_tags": "student, accuplacer, placement, enrollment"
    },
    {
      "id": 3,
      "created_at": "2026-04-19T08:30:00",
      "updated_at": "2026-04-19T08:30:00",
      "closed_at": null,
      "opened_by_staff_id": 3,
      "ticket_type": "Exam Intake",
      "status": "Open",
      "priority": "Normal",
      "origin_source": "Submitted by form",
      "location_id": 1,
      "brief_summary": "Received paper exam packet from Prof. Martinez – HIST 110 makeup, student scheduled 04/22",
      "examinee_id": null,
      "irregularity_id": null,
      "testing_event_id": null,
      "faculty_name": "Prof. Luis Martinez",
      "faculty_email": "lmartinez@columbiastate.edu",
      "external_contact_name": null,
      "external_contact_email": null,
      "initial_comm_type": "Form submission",
      "original_message": "Faculty dropped off sealed exam packet for HIST 110 makeup exam. Student is scheduled for 04/22/2026 at 9:00 AM in Room 114.",
      "exam_type": "Faculty Test",
      "test_medium": "Paper exam",
      "accommodated_exam": false,
      "exam_returned": false,
      "exam_returned_at": null,
      "requires_email": false,
      "email_subject": null,
      "email_body": null,
      "email_recipients": null,
      "log_notes": "04/19/2026 – Exam received and logged into secure storage. Scheduled for 04/22.",
      "resolution_summary": null,
      "category_tags": "exam intake, history, paper exam, faculty test"
    },
    {
      "id": 4,
      "created_at": "2026-04-15T14:20:00",
      "updated_at": "2026-04-20T09:05:00",
      "closed_at": null,
      "opened_by_staff_id": 4,
      "ticket_type": "Irregularity Generated",
      "status": "Open",
      "priority": "Urgent",
      "origin_source": "Created from Irregularity",
      "location_id": 4,
      "brief_summary": "Follow-up required after IRR0002 – examinee misconduct during HiSET session, pending director review",
      "examinee_id": "7654321",
      "irregularity_id": 2,
      "testing_event_id": 2,
      "faculty_name": null,
      "faculty_email": null,
      "external_contact_name": null,
      "external_contact_email": null,
      "initial_comm_type": "Other",
      "original_message": "Irregularity report IRR0002 filed during HiSET Cohort A session at Williamson campus. Student removed from testing room. Director notified on site.",
      "exam_type": "HiSET",
      "test_medium": "Paper exam",
      "accommodated_exam": false,
      "exam_returned": false,
      "exam_returned_at": null,
      "requires_email": true,
      "email_subject": "Notification: Testing Irregularity – Student ID 7654321",
      "email_body": "This is to formally notify you that a testing irregularity (IRR0002 – Examinee Misconduct) was reported on 04/15/2026 during the HiSET Cohort A session at the Williamson campus. This matter is currently under review.",
      "email_recipients": "director@columbiastate.edu",
      "log_notes": "04/15/2026 – Irregularity report filed. Student escorted from testing room. Director notified on site.\n04/17/2026 – Met with director. Formal policy review initiated.\n04/20/2026 – Awaiting director decision. Student placed on hold pending outcome.",
      "resolution_summary": null,
      "category_tags": "irregularity, misconduct, hiset, urgent, policy review"
    },
    {
      "id": 5,
      "created_at": "2026-04-12T10:00:00",
      "updated_at": "2026-04-14T15:30:00",
      "closed_at": "2026-04-14T15:30:00",
      "opened_by_staff_id": 1,
      "ticket_type": "Accessibility Coordination",
      "status": "Closed",
      "priority": "Normal",
      "origin_source": "Submitted by form",
      "location_id": 1,
      "brief_summary": "Coordinated 1.5x extended time exam for accommodated student – ENGL 101 – Jordan Mitchell",
      "examinee_id": "5512984",
      "irregularity_id": null,
      "testing_event_id": null,
      "faculty_name": "Prof. Angela Reeves",
      "faculty_email": "areeves@columbiastate.edu",
      "external_contact_name": null,
      "external_contact_email": null,
      "accessibility_student_name": "Jordan Mitchell",
      "accessibility_student_email": "jmitchell@student.columbiastate.edu",
      "accessibility_employee_contact": "Carla Dean",
      "accessibility_details": "Student has documented accommodation for 1.5x extended time. Quiet room reserved. Exam administered on 04/14/2026 at 10:00 AM without incident.",
      "initial_comm_type": "Form submission",
      "original_message": "Accommodation request submitted through the accessibility office portal. Student Jordan Mitchell needs 1.5x time extension for ENGL 101 midterm with Prof. Reeves on 04/14.",
      "exam_type": "Faculty Test",
      "test_medium": "Paper exam",
      "accommodated_exam": true,
      "exam_returned": true,
      "exam_returned_at": "2026-04-14T16:00:00",
      "requires_email": false,
      "email_subject": null,
      "email_body": null,
      "email_recipients": null,
      "log_notes": "04/12/2026 – Accommodation request received. Quiet room reserved.\n04/13/2026 – Confirmed with faculty. Exam packet received from Prof. Reeves.\n04/14/2026 – Exam administered successfully. Returned to faculty same day.",
      "resolution_summary": "Exam completed with no issues. Student used 1.5x time in quiet room. Exam returned to Prof. Reeves at 4:00 PM on 04/14/2026.",
      "category_tags": "accessibility, accommodation, english, closed, resolved"
    },
    {
      "id": 6,
      "created_at": "2026-04-16T11:10:00",
      "updated_at": "2026-04-18T14:45:00",
      "closed_at": null,
      "opened_by_staff_id": 3,
      "ticket_type": "Vendor Test Coordination",
      "status": "Pending",
      "priority": "Normal",
      "origin_source": "Created from email",
      "location_id": 1,
      "brief_summary": "Pearson testing window rescheduled – coordinating new date with vendor rep T.J. Moreau",
      "examinee_id": null,
      "irregularity_id": null,
      "testing_event_id": 4,
      "faculty_name": null,
      "faculty_email": null,
      "external_contact_name": "T.J. Moreau",
      "external_contact_email": "tjmoreau@pearsonvue.com",
      "initial_comm_type": "Email (pasted-in or auto-captured)",
      "original_message": "Hi, this is T.J. from Pearson VUE. We need to reschedule the Spring 2026 testing window originally set for 04/25. A proctor conflict has come up on our end. Can we move to the week of 05/02?",
      "exam_type": "Pearson",
      "test_medium": "Online exam",
      "accommodated_exam": false,
      "exam_returned": false,
      "exam_returned_at": null,
      "requires_email": true,
      "email_subject": "Re: Spring 2026 Pearson Testing Window Reschedule",
      "email_body": "Hi T.J., thank you for reaching out. We can accommodate the reschedule to the week of 05/02. Please confirm the specific date and we will update our room reservations accordingly.",
      "email_recipients": "tjmoreau@pearsonvue.com",
      "log_notes": "04/16/2026 – Received reschedule request from Pearson vendor rep via email.\n04/18/2026 – Replied confirming availability for week of 05/02. Awaiting vendor confirmation.",
      "resolution_summary": null,
      "category_tags": "pearson, vendor, scheduling, reschedule"
    },
    {
      "id": 7,
      "created_at": "2026-04-20T08:00:00",
      "updated_at": "2026-04-20T08:00:00",
      "closed_at": null,
      "opened_by_staff_id": 2,
      "ticket_type": "Internal Follow-Up",
      "status": "Open",
      "priority": "Low",
      "origin_source": "Created by employee",
      "location_id": 1,
      "brief_summary": "Q2 revision of testing center procedures handbook – assign to staff before end of semester",
      "examinee_id": null,
      "irregularity_id": null,
      "testing_event_id": null,
      "faculty_name": null,
      "faculty_email": null,
      "external_contact_name": null,
      "external_contact_email": null,
      "initial_comm_type": null,
      "original_message": null,
      "exam_type": null,
      "test_medium": null,
      "accommodated_exam": false,
      "exam_returned": false,
      "exam_returned_at": null,
      "requires_email": false,
      "email_subject": null,
      "email_body": null,
      "email_recipients": null,
      "log_notes": "04/20/2026 – Task created. Handbook last updated Q4 2025. Director requested Q2 2026 revision before end of semester.",
      "resolution_summary": null,
      "category_tags": "internal, handbook, procedures, q2"
    }
  ]
}
